README.md
setup.py
deepmux/__init__.py
deepmux/__main__.py
deepmux/api.py
deepmux/cmd.py
deepmux/config.py
deepmux/errors.py
deepmux/templates.py
deepmux_cli.egg-info/PKG-INFO
deepmux_cli.egg-info/SOURCES.txt
deepmux_cli.egg-info/dependency_links.txt
deepmux_cli.egg-info/entry_points.txt
deepmux_cli.egg-info/requires.txt
deepmux_cli.egg-info/top_level.txt