Metadata-Version: 2.1
Name: deepmux-cli
Version: 0.0.8
Summary: UNKNOWN
Home-page: https://github.com/Deep-Mux/deepmux-cli
Author: DeepMux
Author-email: dev@deepmux.com
License: UNKNOWN
Platform: UNKNOWN
Classifier: Development Status :: 3 - Alpha
Classifier: Intended Audience :: Developers
Classifier: Topic :: Software Development :: Build Tools
Classifier: License :: OSI Approved :: MIT License
Classifier: Programming Language :: Python :: 3
Classifier: Programming Language :: Python :: 3.6
Classifier: Programming Language :: Python :: 3.7
Classifier: Programming Language :: Python :: 3.8
Classifier: Programming Language :: Python :: 3.9
